and_gate.v
module and_gate(
    input a,
    input b,
    output y
);
    assign y = a & b;
endmodule

and_gate_tb.v
`include "and_gate.v"
module and_gate_tb();

reg a, b, c,d;

wire e, f;

wire y;

initial begin
    $dumpfile("file.vcd");
    $dumpvars(0, and_gate_tb);

    $display ("time\t a b c d e f y");
    $monitor ("%g\t %b %b %b %b %b %b %b",
        $time, a, b, c, d, e, f, y);
    // a = 1;
    // b = 0;
    // #5 a = 0;
    // #5 b = 1;
    // #5 a = 1;

    //Another way to write the above code
    // a = 0;
    // b = 0;
    // #5 a = 1;
    // #5 b = 1;
    // #5 a = 0;

    //Another way to write the above code
    
    
    // #5 a = 0; b = 0; c = 0; d = 0;
    // #5 a = 0; b = 1; c = 0; d = 1;
    // #5 a = 1; b = 0; c = 1; d = 0;
    // #5 a = 1; b = 1; c = 1; d = 1;

    a = 0; b = 0;
    c = 0; d = 0;
    #5 c = 0; d = 1;
    #5 c = 1; d = 0;
    #5 c = 1; d = 1;
    #5 c = 0; d = 0;
    #5 a = 0; b = 0;
    #5 a = 0; b = 1;
    #5 a = 1; b = 0;
    #5 a = 1; b = 1;
    #5 a = 0; b = 0; c = 0; d = 0;
    #5 a = 0; b = 1; c = 0; d = 1;
    #5 a = 1; b = 0; c = 1; d = 0;
    #5 a = 1; b = 1; c = 1; d = 1;
    #5 a = 0; b = 0; c = 0; d = 0;
    #5 a = 0; b = 0; c = 0; d = 0;
    #5 a = 0; b = 0; c = 0; d = 0;
    #5 a = 0; b = 0; c = 0; d = 0;



    #5 $finish;
end

and_gate U_and_gate (
    a,
    b,
    e
);

 and_gate U_and_gate2 (
    c,
    d,
    f
 );

 and_gate U_and_gate3 (
    e,
    f,
    y
 );

endmodule

file.vcd
$date
	Wed Aug 28 16:57:31 2024
$end
$version
	Icarus Verilog
$end
$timescale
	1s
$end
$scope module and_gate_tb $end
$var wire 1 ! y $end
$var wire 1 " f $end
$var wire 1 # e $end
$var reg 1 $ a $end
$var reg 1 % b $end
$var reg 1 & c $end
$var reg 1 ' d $end
$scope module U_and_gate $end
$var wire 1 $ a $end
$var wire 1 % b $end
$var wire 1 # y $end
$upscope $end
$scope module U_and_gate2 $end
$var wire 1 & a $end
$var wire 1 ' b $end
$var wire 1 " y $end
$upscope $end
$scope module U_and_gate3 $end
$var wire 1 # a $end
$var wire 1 " b $end
$var wire 1 ! y $end
$upscope $end
$upscope $end
$enddefinitions $end
$comment Show the parameter values. $end
$dumpall
$end
#0
$dumpvars
0'
0&
0%
0$
0#
0"
0!
$end
#5
1'
#10
0'
1&
#15
1"
1'
#20
0"
0'
0&
#30
1%
#35
0%
1$
#40
1#
1%
#45
0#
0%
0$
#50
1'
1%
#55
0'
1&
0%
1$
#60
1!
1"
1#
1'
1%
#65
0!
0"
0#
0'
0&
0%
0$
