multiplexer/mux81_st.v
`include "gates.v"
module mux81_st (
    input [7:0] i,  // 8-bit data input
    input [2:0] s,  // 3-bit select input
    output y        // output
);

    wire [7:0] and_out;  // intermediate AND gates output

    custom_and_gate_df a0(.a(i[0]),.s0(~s[0]),.s1(~s[1]),.s2(~s[2]),.y(and_out[0]));
    custom_and_gate_df a1(.a(i[1]),.s0(s[0]),.s1(~s[1]),.s2(~s[2]),.y(and_out[1]));
    custom_and_gate_df a2(.a(i[2]),.s0(~s[0]),.s1(s[1]),.s2(~s[2]),.y(and_out[2]));
    custom_and_gate_df a3(.a(i[3]),.s0(s[0]),.s1(s[1]),.s2(~s[2]),.y(and_out[3]));
    custom_and_gate_df a4(.a(i[4]),.s0(~s[0]),.s1(~s[1]),.s2(s[2]),.y(and_out[4]));
    custom_and_gate_df a5(.a(i[5]),.s0(s[0]),.s1(~s[1]),.s2(s[2]),.y(and_out[5]));
    custom_and_gate_df a6(.a(i[6]),.s0(~s[0]),.s1(s[1]),.s2(s[2]),.y(and_out[6]));
    custom_and_gate_df a7(.a(i[7]),.s0(s[0]),.s1(s[1]),.s2(s[2]),.y(and_out[7]));


    custom_or_gate_df o1(.a(and_out),.y(y));


endmodule

module custom_and_gate_df(
    input a,
    input s0,
    input s1,
    input s2,
    output y
);


    assign y = a & s0 & s1 & s2;
endmodule

module custom_or_gate_df(
    input [7:0] a,
    output y
);
    assign y = a[0] | a[1] | a[2] | a[3] | a[4] | a[5] | a[6] | a[7];
endmodule

multiplexer/mux81_df.v
module mux81_df(
    input [7:0] i,
    input [2:0] s,
    output y
);

assign y = (s == 3'b000) ? i[0] :
             (s == 3'b001) ? i[1] :
             (s == 3'b010) ? i[2] :
             (s == 3'b011) ? i[3] :
             (s == 3'b100) ? i[4] :
             (s == 3'b101) ? i[5] :
             (s == 3'b110) ? i[6] :
             i[7];
endmodule

multiplexer/mux81_bh.v
module mux81_bh(
    input[7:0] i,
    input [2:0] s,
    output reg y
);

always @(*) begin
    case (s)
        3'b000: y = i[0];
        3'b001: y = i[1];
        3'b010: y = i[2];
        3'b011: y = i[3];
        3'b100: y = i[4];
        3'b101: y = i[5];
        3'b110: y = i[6];
        3'b111: y = i[7];
        default: y = 1'b0;
    endcase
end 

endmodule

multiplexer/mux81_tb.v
`include "mux81_df.v"
`include "mux81_bh.v"
`include "mux81_st.v"
module mux81_tb();

reg [7:0] i;
reg [2:0] s;
wire y;

// mux81_df mux1(
//     .i(i),
//     .s(s),
//     .y(y)
// );

mux81_bh mux2(
    .i(i),
    .s(s),
    .y(y)
);

// mux81_st mux3(
//     .i(i),
//     .s(s),
//     .y(y)
// );

initial begin
    $dumpfile("mux81.vcd");
    $dumpvars(0, mux81_tb);

    $display("time\t i        s   y");
    $monitor("%g\t %b %b %b",
    $time, i, s, y);

    // Test case 1
    i = 8'b00000001; s = 3'b000;
    #10 i = 8'b00000010; s = 3'b001;
    #10 i = 8'b00000100; s = 3'b010;
    #10 i = 8'b00001000; s = 3'b011;
    #10 i = 8'b00010000; s = 3'b100;
    #10 i = 8'b00100000; s = 3'b101;
    #10 i = 8'b01000000; s = 3'b110;
    #10 i = 8'b10000000; s = 3'b111;
    #10;
    $finish;
end

endmodule

multiplexer/mux81.vcd
$date
	Tue Sep 24 16:56:28 2024
$end
$version
	Icarus Verilog
$end
$timescale
	1s
$end
$scope module mux81_tb $end
$var wire 1 ! y $end
$var reg 8 " i [7:0] $end
$var reg 3 # s [2:0] $end
$scope module mux2 $end
$var wire 8 $ i [7:0] $end
$var wire 3 % s [2:0] $end
$var reg 1 ! y $end
$upscope $end
$upscope $end
$enddefinitions $end
$comment Show the parameter values. $end
$dumpall
$end
#0
$dumpvars
b0 %
b1 $
b0 #
b1 "
1!
$end
#10
b1 #
b1 %
b10 "
b10 $
#20
b10 #
b10 %
b100 "
b100 $
#30
b11 #
b11 %
b1000 "
b1000 $
#40
b100 #
b100 %
b10000 "
b10000 $
#50
b101 #
b101 %
b100000 "
b100000 $
#60
b110 #
b110 %
b1000000 "
b1000000 $
#70
b111 #
b111 %
b10000000 "
b10000000 $
