multiplexer/mux41_df.v
module mux41_df(
    input i0, i1,i2,i3,s0, s1,
    output y
);
    assign y = (~s0&~s1&i0) | (s0&~s1&i1) | (~s0&s1&i2) | (s0&s1&i3);

endmodule

multiplexer/alt_mux161.v
`include "mux41_df.v"
module alt_mux161(
    input [15:0] i,
    input [3:0] s,
    output y
);
    wire y1, y2, y3, y4;

mux41_df m1(.i0(i[0]), .i1(i[1]), .i2(i[2]), .i3(i[3]), .s0(s[0]), .s1(s[1]), .y(y1));
mux41_df m2(.i0(i[4]), .i1(i[5]), .i2(i[6]), .i3(i[7]), .s0(s[0]), .s1(s[1]), .y(y2));
mux41_df m3(.i0(i[8]), .i1(i[9]), .i2(i[10]), .i3(i[11]), .s0(s[0]), .s1(s[1]), .y(y3));
mux41_df m4(.i0(i[12]), .i1(i[13]), .i2(i[14]), .i3(i[15]), .s0(s[0]), .s1(s[1]), .y(y4));


mux41_df m5(.i0(y1), .i1(y2), .i2(y3), .i3(y4), .s0(s[2]), .s1(s[3]), .y(y));


endmodule

multiplexer/mux161_tb.v
`include "alt_mux161.v"

module test_mux161_tb;

    reg [15:0] i;
    reg [3:0] s;
    wire y;

    alt_mux161 m1(.i(i), .s(s), .y(y));

    initial begin
        $dumpfile("test_mux161.vcd");
        $dumpvars(0, test_mux161_tb);

        $display("time\t i                s   y");
        $monitor("%g\t %b %b %b", $time, i, s, y);

        // Test cases
        i = 16'b0000000000000001; s = 4'b0000;
        #10 i = 16'b0000000000000010; s = 4'b0001;
        #10 i = 16'b0000000000000100; s = 4'b0010;
        #10 i = 16'b0000000000001000; s = 4'b0011;
        #10 i = 16'b0000000000010000; s = 4'b0100;
        #10 i = 16'b0000000000100000; s = 4'b0101;
        #10 i = 16'b0000000001000000; s = 4'b0110;
        #10 i = 16'b0000000010000000; s = 4'b0111;
        #10 i = 16'b0000000100000000; s = 4'b1000;
        #10 i = 16'b0000001000000000; s = 4'b1001;
        #10 i = 16'b0000010000000000; s = 4'b1010;
        #10 i = 16'b0000100000000000; s = 4'b1011;
        #10 i = 16'b0001000000000000; s = 4'b1100;
        #10 i = 16'b0010000000000000; s = 4'b1101;
        #10 i = 16'b0100000000000000; s = 4'b1110;
        #10 i = 16'b1000000000000000; s = 4'b1111;
        #10;
        $finish;
        end

    endmodule

multiplexer/test_mux161.vcd
$date
	Wed Sep 25 13:48:51 2024
$end
$version
	Icarus Verilog
$end
$timescale
	1s
$end
$scope module test_mux161_tb $end
$var wire 1 ! y $end
$var reg 16 " i [15:0] $end
$var reg 4 # s [3:0] $end
$scope module m1 $end
$var wire 16 $ i [15:0] $end
$var wire 4 % s [3:0] $end
$var wire 1 & y4 $end
$var wire 1 ' y3 $end
$var wire 1 ( y2 $end
$var wire 1 ) y1 $end
$var wire 1 ! y $end
$scope module m1 $end
$var wire 1 * i0 $end
$var wire 1 + i1 $end
$var wire 1 , i2 $end
$var wire 1 - i3 $end
$var wire 1 . s0 $end
$var wire 1 / s1 $end
$var wire 1 ) y $end
$upscope $end
$scope module m2 $end
$var wire 1 0 i0 $end
$var wire 1 1 i1 $end
$var wire 1 2 i2 $end
$var wire 1 3 i3 $end
$var wire 1 4 s0 $end
$var wire 1 5 s1 $end
$var wire 1 ( y $end
$upscope $end
$scope module m3 $end
$var wire 1 6 i0 $end
$var wire 1 7 i1 $end
$var wire 1 8 i2 $end
$var wire 1 9 i3 $end
$var wire 1 : s0 $end
$var wire 1 ; s1 $end
$var wire 1 ' y $end
$upscope $end
$scope module m4 $end
$var wire 1 < i0 $end
$var wire 1 = i1 $end
$var wire 1 > i2 $end
$var wire 1 ? i3 $end
$var wire 1 @ s0 $end
$var wire 1 A s1 $end
$var wire 1 & y $end
$upscope $end
$scope module m5 $end
$var wire 1 ) i0 $end
$var wire 1 ( i1 $end
$var wire 1 ' i2 $end
$var wire 1 & i3 $end
$var wire 1 B s0 $end
$var wire 1 C s1 $end
$var wire 1 ! y $end
$upscope $end
$upscope $end
$upscope $end
$enddefinitions $end
$comment Show the parameter values. $end
$dumpall
$end
#0
$dumpvars
0C
0B
0A
0@
0?
0>
0=
0<
0;
0:
09
08
07
06
05
04
03
02
01
00
0/
0.
0-
0,
0+
1*
1)
0(
0'
0&
b0 %
b1 $
b0 #
b1 "
1!
$end
#10
1!
1)
1.
14
1:
1@
0*
1+
b1 #
b1 %
b10 "
b10 $
#20
1!
1)
0.
1/
04
15
0:
1;
0@
1A
0+
1,
b10 #
b10 %
b100 "
b100 $
#30
1.
14
1:
1@
0,
1-
b11 #
b11 %
b1000 "
b1000 $
#40
1(
1!
0)
0.
0/
04
05
0:
0;
0@
0A
1B
0-
10
b100 #
b100 %
b10000 "
b10000 $
#50
1!
1(
1.
14
1:
1@
00
11
b101 #
b101 %
b100000 "
b100000 $
#60
1!
1(
0.
1/
04
15
0:
1;
0@
1A
01
12
b110 #
b110 %
b1000000 "
b1000000 $
#70
1.
14
1:
1@
02
13
b111 #
b111 %
b10000000 "
b10000000 $
#80
1'
1!
0(
0.
0/
04
05
0:
0;
0@
0A
0B
1C
03
16
b1000 #
b1000 %
b100000000 "
b100000000 $
#90
1!
1'
1.
14
1:
1@
06
17
b1001 #
b1001 %
b1000000000 "
b1000000000 $
#100
1!
1'
0.
1/
04
15
0:
1;
0@
1A
07
18
b1010 #
b1010 %
b10000000000 "
b10000000000 $
#110
1.
14
1:
1@
08
19
b1011 #
b1011 %
b100000000000 "
b100000000000 $
#120
1&
1!
0'
0.
0/
04
05
0:
0;
0@
0A
1B
09
1<
b1100 #
b1100 %
b1000000000000 "
b1000000000000 $
#130
1!
1&
1.
14
1:
1@
0<
1=
b1101 #
b1101 %
b10000000000000 "
b10000000000000 $
#140
1!
1&
0.
1/
04
15
0:
1;
0@
1A
0=
1>
b1110 #
b1110 %
b100000000000000 "
b100000000000000 $
#150
1.
14
1:
1@
0>
1?
b1111 #
b1111 %
b1000000000000000 "
b1000000000000000 $
