adders/full_adders_bh.v
module full_adders_bh(
    input a,
    input b,
    input c,
    output reg sum,
    output reg carry
);

always @(*) begin
    sum = a ^ b ^c;
    carry = (a & b) | ((a ^ b) & c);
end

endmodule

adders/full_adders_df.v
module full_adders_df (
    input a,
    input b,
    input c,
    output sum,
    output carry
);
assign sum = a ^ b ^ c;
assign carry = (a & b) | (c & (a ^ b));
endmodule

gates/or_gate_st.v
module or_gate_st(
    input a,
    input b,
    output y
);

or(y,a,b);

endmodule

adders/half_adders_df.v
module half_adders_df (
    input a,
    input b,
    output sum,
    output carry
);
     assign sum =  a ^ b;
     assign carry = a & b;

endmodule

adders/full_adders_st.v
`include "half_adders_df.v"
`include "or_gate_st.v"
module full_adders_st (
    input a,
    input b,
    input c,
    output sum,
    output carry
);

    half_adders_df h1(a,b,x,y);
    half_adders_df h2(x,c,sum,z);
    or_gate_st o1(y,z,carry);

endmodule

adders/full_adders_tb.v
`include "full_adders_df.v"
`include "full_adders_bh.v"
`include "full_adders_st.v"

module full_adders_tb();

reg a,b,c;
wire sum, carry;

initial begin
    $dumpfile("adders.vcd");
    $dumpvars(0, full_adders_tb);

    $display("time\t a b c sum car ");
    $monitor("%g\t %b %b %b  %b   %b",
        $time, a, b, c, sum, carry);
    
    a = 0; b = 0; c = 0;
    #5 a = 0; b = 0; c = 1;
    #5 a = 0; b = 1; c = 0;
    #5 a = 0; b = 1; c = 1;
    #5 a = 1; b = 0; c = 0;
    #5 a = 1; b = 0; c = 1;
    #5 a = 1; b = 1; c = 0;
    #5 a = 1; b = 1; c = 1;
    #5 $finish;
end

//uncomment which one to use 
// full_adders_df f1(a,b,c,sum,carry);
// full_adders_bh f2(a,b,c,sum,carry);
full_adders_st f3(a,b,c,sum,carry);

endmodule

adders/adders.vcd
$date
	Wed Sep 18 14:06:54 2024
$end
$version
	Icarus Verilog
$end
$timescale
	1s
$end
$scope module full_adders_tb $end
$var wire 1 ! sum $end
$var wire 1 " carry $end
$var reg 1 # a $end
$var reg 1 $ b $end
$var reg 1 % c $end
$scope module f3 $end
$var wire 1 # a $end
$var wire 1 $ b $end
$var wire 1 % c $end
$var wire 1 & z $end
$var wire 1 ' y $end
$var wire 1 ( x $end
$var wire 1 ! sum $end
$var wire 1 " carry $end
$scope module h1 $end
$var wire 1 # a $end
$var wire 1 $ b $end
$var wire 1 ' carry $end
$var wire 1 ( sum $end
$upscope $end
$scope module h2 $end
$var wire 1 ( a $end
$var wire 1 % b $end
$var wire 1 & carry $end
$var wire 1 ! sum $end
$upscope $end
$scope module o1 $end
$var wire 1 ' a $end
$var wire 1 & b $end
$var wire 1 " y $end
$upscope $end
$upscope $end
$upscope $end
$enddefinitions $end
$comment Show the parameter values. $end
$dumpall
$end
#0
$dumpvars
0(
0'
0&
0%
0$
0#
0"
0!
$end
#5
1!
1%
#10
1(
0%
1$
#15
1"
0!
1&
1%
#20
0"
1!
0&
0%
0$
1#
#25
1"
0!
1&
1%
#30
0&
0(
1'
0%
1$
#35
1!
1%
