adders/full_subtractor_df.v
module full_subtractor_df (
    input a,
    input b,
    input c,
    output difference,
    output borrow
);
assign difference = a ^ b ^ c;
assign borrow = (~a & b) | (b & c) | (~a & c);
endmodule

gates/or_gate_st.v
module or_gate_st(
    input a,
    input b,
    output y
);

or(y,a,b);

endmodule

adders/half_adders_df.v
module half_adders_df (
    input a,
    input b,
    output sum,
    output carry
);
     assign sum =  a ^ b;
     assign carry = a & b;

endmodule

adders/full_adders_st.v
`include "half_adders_df.v"
`include "or_gate_st.v"
module full_adders_st (
    input a,
    input b,
    input c,
    output sum,
    output carry
);

    half_adders_df h1(a,b,x,y);
    half_adders_df h2(x,c,sum,z);
    or_gate_st o1(y,z,carry);

endmodule

adders/full_adder_subtractor_st.v
`include "full_adders_st.v"
`include "full_subtractor_df.v"
module full_adder_subtractor_st(
    input a,
    input b,
    input cin,
    input control,
    output result,
    output cout
);

wire sum, diff, carry, borrow;

full_adders_st adder (
    .a(a),
    .b(b),
    .c(cin),
    .sum(sum),
    .carry(carry)
    );

full_subtractor_df subtractor (
    .a(a),
    .b(b),
    .c(cin),
    .difference(diff),
    .borrow(borrow)
);

assign result = control ? diff : sum;
assign cout = control ? borrow : carry;

endmodule

adders/4bit_full_adder_subtractor_st.v
`include "full_adder_subtractor_st.v"
module four_bit_full_adder_subtractor_st (
    input [3:0] a,
    input [3:0] b,
    input cin,
    input control,
    output [3:0] result,
    output cout
);
wire [2:0] carry;


full_adder_subtractor_st u1 (
    .a(a[0]),
    .b(b[0]),
    .cin(cin),
    .control(control),
    .result(result[0]),
    .cout(carry[0])
);

full_adder_subtractor_st u2 (
    .a(a[1]),
    .b(b[1]),
    .cin(carry[0]),
    .control(control),
    .result(result[1]),
    .cout(carry[1])
);

full_adder_subtractor_st u3 (
    .a(a[2]),
    .b(b[2]),
    .cin(carry[1]),
    .control(control),
    .result(result[2]),
    .cout(carry[2])
);

full_adder_subtractor_st u4 (
    .a(a[3]),
    .b(b[3]),
    .cin(carry[2]),
    .control(control),
    .result(result[3]),
    .cout(cout)
);


endmodule

adders/4bit_full_adder_subtractor_tb.v
`timescale 1ns/1ps
`include "4bit_full_adder_subtractor_st.v"

module four_bit_full_adder_subtractor_st_tb;
    reg [3:0] a, b;
    reg cin, control;
    wire [3:0] result;
    wire cout;

    four_bit_full_adder_subtractor_st uut (
        .a(a), .b(b), 
        .cin(cin), 
        .control(control), 
        .result(result), 
        .cout(cout)
    );

    // Initial display
    initial begin
            $dumpfile("four.vcd");
    $dumpvars(0, four_bit_full_adder_subtractor_st_tb);
        $display("Time\t A      B      Cin   Control   Result   Cout");
    end

    // Test variables
    integer i, j, k, l;
    integer pass_count = 0, fail_count = 0;

    task check_result;
        input [3:0] a_in, b_in;
        input cin_in, control_in;
        input [3:0] expected_result;
        input expected_cout;
        begin
            #10; // Propagation delay

            // Determine expected result and cout based on control signal
            if (control_in == 0) begin // Addition mode
                {expected_cout, expected_result} = a_in + b_in + cin_in;
            end else begin // Subtraction mode
                {expected_cout, expected_result} = (cin_in == 0) ? (a_in - b_in) : (a_in - b_in - 1);
            end

            // Compare the actual result and cout with expected result
            if (result === expected_result && cout === expected_cout) begin
                pass_count = pass_count + 1;
            end else begin
                fail_count = fail_count + 1;
            end
        end
    endtask

    initial begin
        // Nested loops for comprehensive testing
        for (i = 0; i < 2; i = i + 1) begin      // control
            for (j = 0; j < 2; j = j + 1) begin  // cin
                for (k = 0; k < 16; k = k + 1) begin // a
                    for (l = 0; l < 16; l = l + 1) begin // b
                        // Set inputs
                        control = i;
                        cin = j;
                        a = k;
                        b = l;

                        // Display the test case result
                        $display("%0t\t %b   %b   %b     %b       %b     %b", $time, a, b, cin, control, result, cout);
                        
                        // Verify result
                        check_result(a, b, cin, control, 
                                     (control ? (a - b - cin) : (a + b + cin)),
                                     (control ? (a < b + cin) : (a + b + cin > 15)));
                    end
                end
            end
        end

        // Final report
        $display("\nTest Complete:");
        $display("PASS COUNT: %0d", pass_count);
        $display("FAIL COUNT: %0d", fail_count);

        $finish;
    end
endmodule

adders/four.vcd
$date
	Tue Dec 17 12:07:39 2024
$end
$version
	Icarus Verilog
$end
$timescale
	1ps
$end
$scope module four_bit_full_adder_subtractor_st_tb $end
$var wire 4 ! result [3:0] $end
$var wire 1 " cout $end
$var reg 4 # a [3:0] $end
$var reg 4 $ b [3:0] $end
$var reg 1 % cin $end
$var reg 1 & control $end
$var integer 32 ' fail_count [31:0] $end
$var integer 32 ( i [31:0] $end
$var integer 32 ) j [31:0] $end
$var integer 32 * k [31:0] $end
$var integer 32 + l [31:0] $end
$var integer 32 , pass_count [31:0] $end
$scope module uut $end
$var wire 4 - a [3:0] $end
$var wire 4 . b [3:0] $end
$var wire 1 % cin $end
$var wire 1 & control $end
$var wire 4 / result [3:0] $end
$var wire 1 " cout $end
$var wire 3 0 carry [2:0] $end
$scope module u1 $end
$var wire 1 1 a $end
$var wire 1 2 b $end
$var wire 1 % cin $end
$var wire 1 & control $end
$var wire 1 3 sum $end
$var wire 1 4 result $end
$var wire 1 5 diff $end
$var wire 1 6 cout $end
$var wire 1 7 carry $end
$var wire 1 8 borrow $end
$scope module adder $end
$var wire 1 1 a $end
$var wire 1 2 b $end
$var wire 1 % c $end
$var wire 1 9 z $end
$var wire 1 : y $end
$var wire 1 ; x $end
$var wire 1 3 sum $end
$var wire 1 7 carry $end
$scope module h1 $end
$var wire 1 1 a $end
$var wire 1 2 b $end
$var wire 1 : carry $end
$var wire 1 ; sum $end
$upscope $end
$scope module h2 $end
$var wire 1 ; a $end
$var wire 1 % b $end
$var wire 1 9 carry $end
$var wire 1 3 sum $end
$upscope $end
$scope module o1 $end
$var wire 1 : a $end
$var wire 1 9 b $end
$var wire 1 7 y $end
$upscope $end
$upscope $end
$scope module subtractor $end
$var wire 1 1 a $end
$var wire 1 2 b $end
$var wire 1 8 borrow $end
$var wire 1 % c $end
$var wire 1 5 difference $end
$upscope $end
$upscope $end
$scope module u2 $end
$var wire 1 < a $end
$var wire 1 = b $end
$var wire 1 > cin $end
$var wire 1 & control $end
$var wire 1 ? sum $end
$var wire 1 @ result $end
$var wire 1 A diff $end
$var wire 1 B cout $end
$var wire 1 C carry $end
$var wire 1 D borrow $end
$scope module adder $end
$var wire 1 < a $end
$var wire 1 = b $end
$var wire 1 > c $end
$var wire 1 E z $end
$var wire 1 F y $end
$var wire 1 G x $end
$var wire 1 ? sum $end
$var wire 1 C carry $end
$scope module h1 $end
$var wire 1 < a $end
$var wire 1 = b $end
$var wire 1 F carry $end
$var wire 1 G sum $end
$upscope $end
$scope module h2 $end
$var wire 1 G a $end
$var wire 1 > b $end
$var wire 1 E carry $end
$var wire 1 ? sum $end
$upscope $end
$scope module o1 $end
$var wire 1 F a $end
$var wire 1 E b $end
$var wire 1 C y $end
$upscope $end
$upscope $end
$scope module subtractor $end
$var wire 1 < a $end
$var wire 1 = b $end
$var wire 1 D borrow $end
$var wire 1 > c $end
$var wire 1 A difference $end
$upscope $end
$upscope $end
$scope module u3 $end
$var wire 1 H a $end
$var wire 1 I b $end
$var wire 1 J cin $end
$var wire 1 & control $end
$var wire 1 K sum $end
$var wire 1 L result $end
$var wire 1 M diff $end
$var wire 1 N cout $end
$var wire 1 O carry $end
$var wire 1 P borrow $end
$scope module adder $end
$var wire 1 H a $end
$var wire 1 I b $end
$var wire 1 J c $end
$var wire 1 Q z $end
$var wire 1 R y $end
$var wire 1 S x $end
$var wire 1 K sum $end
$var wire 1 O carry $end
$scope module h1 $end
$var wire 1 H a $end
$var wire 1 I b $end
$var wire 1 R carry $end
$var wire 1 S sum $end
$upscope $end
$scope module h2 $end
$var wire 1 S a $end
$var wire 1 J b $end
$var wire 1 Q carry $end
$var wire 1 K sum $end
$upscope $end
$scope module o1 $end
$var wire 1 R a $end
$var wire 1 Q b $end
$var wire 1 O y $end
$upscope $end
$upscope $end
$scope module subtractor $end
$var wire 1 H a $end
$var wire 1 I b $end
$var wire 1 P borrow $end
$var wire 1 J c $end
$var wire 1 M difference $end
$upscope $end
$upscope $end
$scope module u4 $end
$var wire 1 T a $end
$var wire 1 U b $end
$var wire 1 V cin $end
$var wire 1 & control $end
$var wire 1 W sum $end
$var wire 1 X result $end
$var wire 1 Y diff $end
$var wire 1 " cout $end
$var wire 1 Z carry $end
$var wire 1 [ borrow $end
$scope module adder $end
$var wire 1 T a $end
$var wire 1 U b $end
$var wire 1 V c $end
$var wire 1 \ z $end
$var wire 1 ] y $end
$var wire 1 ^ x $end
$var wire 1 W sum $end
$var wire 1 Z carry $end
$scope module h1 $end
$var wire 1 T a $end
$var wire 1 U b $end
$var wire 1 ] carry $end
$var wire 1 ^ sum $end
$upscope $end
$scope module h2 $end
$var wire 1 ^ a $end
$var wire 1 V b $end
$var wire 1 \ carry $end
$var wire 1 W sum $end
$upscope $end
$scope module o1 $end
$var wire 1 ] a $end
$var wire 1 \ b $end
$var wire 1 Z y $end
$upscope $end
$upscope $end
$scope module subtractor $end
$var wire 1 T a $end
$var wire 1 U b $end
$var wire 1 [ borrow $end
$var wire 1 V c $end
$var wire 1 Y difference $end
$upscope $end
$upscope $end
$upscope $end
$scope task check_result $end
$var reg 4 _ a_in [3:0] $end
$var reg 4 ` b_in [3:0] $end
$var reg 1 a cin_in $end
$var reg 1 b control_in $end
$var reg 1 c expected_cout $end
$var reg 4 d expected_result [3:0] $end
$upscope $end
$upscope $end
$enddefinitions $end
$comment Show the parameter values. $end
$dumpall
$end
#0
$dumpvars
b0 d
0c
0b
0a
b0 `
b0 _
0^
0]
0\
0[
0Z
0Y
0X
0W
0V
0U
0T
0S
0R
0Q
0P
0O
0N
0M
0L
0K
0J
0I
0H
0G
0F
0E
0D
0C
0B
0A
0@
0?
0>
0=
0<
0;
0:
09
08
07
06
05
04
03
02
01
b0 0
b0 /
b0 .
b0 -
b0 ,
b0 +
b0 *
b0 )
b0 (
b0 '
0&
0%
b0 $
b0 #
0"
b0 !
$end
#10000
b1 !
b1 /
14
18
13
15
1;
12
b1 d
b1 `
b1 $
b1 .
b1 +
b1 ,
#20000
04
08
b10 !
b10 /
1@
1D
03
05
1?
1A
0;
1G
02
1=
b10 d
b10 `
b10 $
b10 .
b10 +
b10 ,
#30000
b11 !
b11 /
14
18
13
15
1;
12
b11 d
b11 `
b11 $
b11 .
b11 +
b11 ,
#40000
04
08
0@
0D
b100 !
b100 /
1L
1P
03
05
0?
0A
1K
1M
0;
0G
1S
02
0=
1I
b100 d
b100 `
b100 $
b100 .
b100 +
b100 ,
#50000
b101 !
b101 /
14
18
13
15
1;
12
b101 d
b101 `
b101 $
b101 .
b101 +
b101 ,
#60000
04
08
b110 !
b110 /
1@
1D
03
05
1?
1A
0;
1G
02
1=
b110 d
b110 `
b110 $
b110 .
b110 +
b110 ,
#70000
b111 !
b111 /
14
18
13
15
1;
12
b111 d
b111 `
b111 $
b111 .
b111 +
b111 ,
#80000
04
08
0@
0D
0L
0P
b1000 !
b1000 /
1X
1[
03
05
0?
0A
0K
0M
1W
1Y
0;
0G
0S
1^
02
0=
0I
1U
b1000 d
b1000 `
b1000 $
b1000 .
b1000 +
b1000 ,
#90000
b1001 !
b1001 /
14
18
13
15
1;
12
b1001 d
b1001 `
b1001 $
b1001 .
b1001 +
b1001 ,
#100000
04
08
b1010 !
b1010 /
1@
1D
03
05
1?
1A
0;
1G
02
1=
b1010 d
b1010 `
b1010 $
b1010 .
b1010 +
b1010 ,
#110000
b1011 !
b1011 /
14
18
13
15
1;
12
b1011 d
b1011 `
b1011 $
b1011 .
b1011 +
b1011 ,
#120000
04
08
0@
0D
b1100 !
b1100 /
1L
1P
03
05
0?
0A
1K
1M
0;
0G
1S
02
0=
1I
b1100 d
b1100 `
b1100 $
b1100 .
b1100 +
b1100 ,
#130000
b1101 !
b1101 /
14
18
13
15
1;
12
b1101 d
b1101 `
b1101 $
b1101 .
b1101 +
b1101 ,
#140000
04
08
b1110 !
b1110 /
1@
1D
03
05
1?
1A
0;
1G
02
1=
b1110 d
b1110 `
b1110 $
b1110 .
b1110 +
b1110 ,
#150000
b1111 !
b1111 /
14
18
13
15
1;
12
b1111 d
b1111 `
b1111 $
b1111 .
b1111 +
b1111 ,
#160000
08
0@
0D
0L
0P
b1 !
b1 /
0X
0[
0?
0A
0K
0M
0W
0Y
0G
0S
0^
02
0=
0I
0U
11
b1 d
b0 `
b1 _
b0 $
b0 .
b1 #
b1 -
b1 *
b0 +
b10000 ,
#170000
1@
1D
1?
1A
1>
b10 !
b10 /
04
b1 0
16
03
17
05
0;
1:
12
b10 d
b1 `
b1 $
b1 .
b1 +
b10001 ,
#180000
0L
0P
0K
0M
0J
0>
0B
14
b0 0
06
b11 !
b11 /
1@
0C
13
07
15
1?
0E
1A
1;
0:
1G
02
1=
b11 d
b10 `
b10 $
b10 .
b10 +
b10010 ,
#190000
1L
1P
1K
1M
1J
1B
0@
1C
0?
1E
0A
1>
b100 !
b100 /
04
b11 0
16
03
17
05
0;
1:
12
b100 d
b11 `
b11 $
b11 .
b11 +
b10011 ,
#200000
0X
0[
0D
0W
0Y
0J
0V
0>
0B
0N
14
b0 0
06
0@
0C
b101 !
b101 /
1L
0O
13
07
15
0?
0E
0A
1K
0Q
1M
1;
0:
0G
1S
02
0=
1I
b101 d
b100 `
b100 $
b100 .
b100 +
b10100 ,
#210000
1@
1D
1?
1A
1>
b110 !
b110 /
04
b1 0
16
03
17
05
0;
1:
12
b110 d
b101 `
b101 $
b101 .
b101 +
b10101 ,
#220000
0X
0[
0W
0Y
0V
0N
1L
0O
1K
0Q
1M
0J
0>
0B
14
b0 0
06
b111 !
b111 /
1@
0C
13
07
15
1?
0E
1A
1;
0:
1G
02
1=
b111 d
b110 `
b110 $
b110 .
b110 +
b10110 ,
#230000
1X
1[
1W
1Y
1V
1N
0L
1O
0K
1Q
0M
1J
1B
0@
1C
0?
1E
0A
1>
b1000 !
b1000 /
04
b111 0
16
03
17
05
0;
1:
12
b1000 d
b111 `
b111 $
b111 .
b111 +
b10111 ,
#240000
0P
0D
0J
0V
0>
0B
0N
0"
14
b0 0
06
0@
0C
0L
0O
b1001 !
b1001 /
1X
0Z
13
07
15
0?
0E
0A
0K
0Q
0M
1W
0\
1Y
1;
0:
0G
0S
1^
02
0=
0I
1U
b1001 d
b1000 `
b1000 $
b1000 .
b1000 +
b11000 ,
#250000
1@
1D
1?
1A
1>
b1010 !
b1010 /
04
b1 0
16
03
17
05
0;
1:
12
b1010 d
b1001 `
b1001 $
b1001 .
b1001 +
b11001 ,
#260000
0L
0P
0K
0M
0J
0>
0B
14
b0 0
06
b1011 !
b1011 /
1@
0C
13
07
15
1?
0E
1A
1;
0:
1G
02
1=
b1011 d
b1010 `
b1010 $
b1010 .
b1010 +
b11010 ,
#270000
1L
1P
1K
1M
1J
1B
0@
1C
0?
1E
0A
1>
b1100 !
b1100 /
04
b11 0
16
03
17
05
0;
1:
12
b1100 d
b1011 `
b1011 $
b1011 .
b1011 +
b11011 ,
#280000
0"
1X
0Z
0D
1W
0\
1Y
0J
0V
0>
0B
0N
14
b0 0
06
0@
0C
b1101 !
b1101 /
1L
0O
13
07
15
0?
0E
0A
1K
0Q
1M
1;
0:
0G
1S
02
0=
1I
b1101 d
b1100 `
b1100 $
b1100 .
b1100 +
b11100 ,
#290000
1@
1D
1?
1A
1>
b1110 !
b1110 /
04
b1 0
16
03
17
05
0;
1:
12
b1110 d
b1101 `
b1101 $
b1101 .
b1101 +
b11101 ,
#300000
0"
1X
0Z
1W
0\
1Y
0V
0N
1L
0O
1K
0Q
1M
0J
0>
0B
14
b0 0
06
b1111 !
b1111 /
1@
0C
13
07
15
1?
0E
1A
1;
0:
1G
02
1=
b1111 d
b1110 `
b1110 $
b1110 .
b1110 +
b11110 ,
#310000
1"
0X
1Z
0W
1\
0Y
1V
1N
0L
1O
0K
1Q
0M
1J
1B
0@
1C
0?
1E
0A
1>
b0 !
b0 /
04
b111 0
16
03
17
05
0;
1:
12
1c
b0 d
b1111 `
b1111 $
b1111 .
b1111 +
b11111 ,
#320000
0P
0J
0[
0B
1@
0C
0V
1?
0E
1A
0N
0"
0>
0L
0O
b10 !
b10 /
0X
0Z
b0 0
06
0D
0K
0Q
0M
0W
0\
0Y
07
0S
0^
0:
02
0=
0I
0U
01
1<
0c
b10 d
b0 `
b10 _
b0 $
b0 .
b10 #
b10 -
b10 *
b0 +
b100000 ,
#330000
b11 !
b11 /
14
18
13
15
1;
12
b11 d
b1 `
b1 $
b1 .
b1 +
b100001 ,
#340000
1L
1P
1K
1M
1J
04
08
b100 !
b100 /
0@
b10 0
1B
03
05
0?
1C
0A
0;
0G
1F
02
1=
b100 d
b10 `
b10 $
b10 .
b10 +
b100010 ,
#350000
b101 !
b101 /
14
18
13
15
1;
12
b101 d
b11 `
b11 $
b11 .
b11 +
b100011 ,
#360000
0X
0[
0W
0Y
0V
0J
0N
04
08
1@
b0 0
0B
b110 !
b110 /
1L
0O
03
05
1?
0C
1A
1K
0Q
1M
0;
1G
0F
1S
02
0=
1I
b110 d
b100 `
b100 $
b100 .
b100 +
b100100 ,
#370000
b111 !
b111 /
14
18
13
15
1;
12
b111 d
b101 `
b101 $
b101 .
b101 +
b100101 ,
#380000
1X
1[
1W
1Y
1V
1N
0L
1O
0K
1Q
0M
1J
04
08
b1000 !
b1000 /
0@
b110 0
1B
03
05
0?
1C
0A
0;
0G
1F
02
1=
b1000 d
b110 `
b110 $
b110 .
b110 +
b100110 ,
#390000
b1001 !
b1001 /
14
18
13
15
1;
12
b1001 d
b111 `
b111 $
b111 .
b111 +
b100111 ,
#400000
0P
0V
0J
0N
0"
04
08
1@
b0 0
0B
0L
0O
b1010 !
b1010 /
1X
0Z
03
05
1?
0C
1A
0K
0Q
0M
1W
0\
1Y
0;
1G
0F
0S
1^
02
0=
0I
1U
b1010 d
b1000 `
b1000 $
b1000 .
b1000 +
b101000 ,
#410000
b1011 !
b1011 /
14
18
13
15
1;
12
b1011 d
b1001 `
b1001 $
b1001 .
b1001 +
b101001 ,
#420000
1L
1P
1K
1M
1J
04
08
b1100 !
b1100 /
0@
b10 0
1B
03
05
0?
1C
0A
0;
0G
1F
02
1=
b1100 d
b1010 `
b1010 $
b1010 .
b1010 +
b101010 ,
#430000
b1101 !
b1101 /
14
18
13
15
1;
12
b1101 d
b1011 `
b1011 $
b1011 .
b1011 +
b101011 ,
#440000
0"
1X
0Z
1W
0\
1Y
0V
0J
0N
04
08
1@
b0 0
0B
b1110 !
b1110 /
1L
0O
03
05
1?
0C
1A
1K
0Q
1M
0;
1G
0F
1S
02
0=
1I
b1110 d
b1100 `
b1100 $
b1100 .
b1100 +
b101100 ,
#450000
b1111 !
b1111 /
14
18
13
15
1;
12
b1111 d
b1101 `
b1101 $
b1101 .
b1101 +
b101101 ,
#460000
1"
0X
1Z
0W
1\
0Y
1V
1N
0L
1O
0K
1Q
0M
1J
04
08
b0 !
b0 /
0@
b110 0
1B
03
05
0?
1C
0A
0;
0G
1F
02
1=
1c
b0 d
b1110 `
b1110 $
b1110 .
b1110 +
b101110 ,
#470000
b1 !
b1 /
14
18
13
15
1;
12
b1 d
b1111 `
b1111 $
b1111 .
b1111 +
b101111 ,
#480000
0[
0P
0V
0J
0N
0"
08
1@
b0 0
0B
0L
0O
b11 !
b11 /
0X
0Z
1?
0C
1A
0K
0Q
0M
0W
0\
0Y
1G
0F
0S
0^
02
0=
0I
0U
11
0c
b11 d
b0 `
b11 _
b0 $
b0 .
b11 #
b11 -
b11 *
b0 +
b110000 ,
#490000
1L
1P
1K
1M
1J
1B
0@
1C
0?
1E
0A
1>
b100 !
b100 /
04
b11 0
16
03
17
05
0;
1:
12
b100 d
b1 `
b1 $
b1 .
b1 +
b110001 ,
#500000
0>
14
b10 0
06
b101 !
b101 /
0@
0D
13
07
15
0?
0E
0A
1;
0:
0G
1F
02
1=
b101 d
b10 `
b10 $
b10 .
b10 +
b110010 ,
#510000
1D
1@
1?
1A
1>
b110 !
b110 /
04
b11 0
16
03
17
05
0;
1:
12
b110 d
b11 `
b11 $
b11 .
b11 +
b110011 ,
#520000
0X
0[
0W
0Y
0V
0>
0J
0N
14
06
1@
b0 0
0B
0D
b111 !
b111 /
1L
0O
13
07
15
1?
0E
0C
1A
1K
0Q
1M
1;
0:
1G
0F
1S
02
0=
1I
b111 d
b100 `
b100 $
b100 .
b100 +
b110100 ,
#530000
1X
1[
1W
1Y
1V
1N
0L
1O
0K
1Q
0M
1J
1B
0@
1C
0?
1E
0A
1>
b1000 !
b1000 /
04
b111 0
16
03
17
05
0;
1:
12
b1000 d
b101 `
b101 $
b101 .
b101 +
b110101 ,
#540000
0>
14
b110 0
06
b1001 !
b1001 /
0@
0D
13
07
15
0?
0E
0A
1;
0:
0G
1F
02
1=
b1001 d
b110 `
b110 $
b110 .
b110 +
b110110 ,
#550000
1D
1@
1?
1A
1>
b1010 !
b1010 /
04
b111 0
16
03
17
05
0;
1:
12
b1010 d
b111 `
b111 $
b111 .
b111 +
b110111 ,
#560000
0P
0V
0>
0J
0N
0"
14
06
1@
b0 0
0B
0D
0L
0O
b1011 !
b1011 /
1X
0Z
13
07
15
1?
0E
0C
1A
0K
0Q
0M
1W
0\
1Y
1;
0:
1G
0F
0S
1^
02
0=
0I
1U
b1011 d
b1000 `
b1000 $
b1000 .
b1000 +
b111000 ,
#570000
1L
1P
1K
1M
1J
1B
0@
1C
0?
1E
0A
1>
b1100 !
b1100 /
04
b11 0
16
03
17
05
0;
1:
12
b1100 d
b1001 `
b1001 $
b1001 .
b1001 +
b111001 ,
#580000
0>
14
b10 0
06
b1101 !
b1101 /
0@
0D
13
07
15
0?
0E
0A
1;
0:
0G
1F
02
1=
b1101 d
b1010 `
b1010 $
b1010 .
b1010 +
b111010 ,
#590000
1D
1@
1?
1A
1>
b1110 !
b1110 /
04
b11 0
16
03
17
05
0;
1:
12
b1110 d
b1011 `
b1011 $
b1011 .
b1011 +
b111011 ,
#600000
0"
1X
0Z
1W
0\
1Y
0V
0>
0J
0N
14
06
1@
b0 0
0B
0D
b1111 !
b1111 /
1L
0O
13
07
15
1?
0E
0C
1A
1K
0Q
1M
1;
0:
1G
0F
1S
02
0=
1I
b1111 d
b1100 `
b1100 $
b1100 .
b1100 +
b111100 ,
#610000
1"
0X
1Z
0W
1\
0Y
1V
1N
0L
1O
0K
1Q
0M
1J
1B
0@
1C
0?
1E
0A
1>
b0 !
b0 /
04
b111 0
16
03
17
05
0;
1:
12
1c
b0 d
b1101 `
b1101 $
b1101 .
b1101 +
b111101 ,
#620000
0>
14
b110 0
06
b1 !
b1 /
0@
0D
13
07
15
0?
0E
0A
1;
0:
0G
1F
02
1=
b1 d
b1110 `
b1110 $
b1110 .
b1110 +
b111110 ,
#630000
1D
1@
1?
1A
1>
b10 !
b10 /
04
b111 0
16
03
17
05
0;
1:
12
b10 d
b1111 `
b1111 $
b1111 .
b1111 +
b111111 ,
#640000
0[
0V
0N
0@
0D
1L
0O
0?
0A
1K
0Q
1M
0"
0>
0J
b100 !
b100 /
0X
0Z
06
b0 0
0B
0P
0W
0\
0Y
07
0C
0^
0:
0F
02
0=
0I
0U
01
0<
1H
0c
b100 d
b0 `
b100 _
b0 $
b0 .
b100 #
b100 -
b100 *
b0 +
b1000000 ,
#650000
b101 !
b101 /
14
18
13
15
1;
12
b101 d
b1 `
b1 $
b1 .
b1 +
b1000001 ,
#660000
04
08
b110 !
b110 /
1@
1D
03
05
1?
1A
0;
1G
02
1=
b110 d
b10 `
b10 $
b10 .
b10 +
b1000010 ,
#670000
b111 !
b111 /
14
18
13
15
1;
12
b111 d
b11 `
b11 $
b11 .
b11 +
b1000011 ,
#680000
1X
1[
1W
1Y
1V
04
08
0@
0D
b1000 !
b1000 /
0L
b100 0
1N
03
05
0?
0A
0K
1O
0M
0;
0G
0S
1R
02
0=
1I
b1000 d
b100 `
b100 $
b100 .
b100 +
b1000100 ,
#690000
b1001 !
b1001 /
14
18
13
15
1;
12
b1001 d
b101 `
b101 $
b101 .
b101 +
b1000101 ,
#700000
04
08
b1010 !
b1010 /
1@
1D
03
05
1?
1A
0;
1G
02
1=
b1010 d
b110 `
b110 $
b110 .
b110 +
b1000110 ,
#710000
b1011 !
b1011 /
14
18
13
15
1;
12
b1011 d
b111 `
b111 $
b111 .
b111 +
b1000111 ,
#720000
0V
0"
04
08
0@
0D
1L
b0 0
0N
b1100 !
b1100 /
1X
0Z
03
05
0?
0A
1K
0O
1M
1W
0\
1Y
0;
0G
1S
0R
1^
02
0=
0I
1U
b1100 d
b1000 `
b1000 $
b1000 .
b1000 +
b1001000 ,
#730000
b1101 !
b1101 /
14
18
13
15
1;
12
b1101 d
b1001 `
b1001 $
b1001 .
b1001 +
b1001001 ,
#740000
04
08
b1110 !
b1110 /
1@
1D
03
05
1?
1A
0;
1G
02
1=
b1110 d
b1010 `
b1010 $
b1010 .
b1010 +
b1001010 ,
#750000
b1111 !
b1111 /
14
18
13
15
1;
12
b1111 d
b1011 `
b1011 $
b1011 .
b1011 +
b1001011 ,
#760000
1"
0X
1Z
0W
1\
0Y
1V
04
08
0@
0D
b0 !
b0 /
0L
b100 0
1N
03
05
0?
0A
0K
1O
0M
0;
0G
0S
1R
02
0=
1I
1c
b0 d
b1100 `
b1100 $
b1100 .
b1100 +
b1001100 ,
#770000
b1 !
b1 /
14
18
13
15
1;
12
b1 d
b1101 `
b1101 $
b1101 .
b1101 +
b1001101 ,
#780000
04
08
b10 !
b10 /
1@
1D
03
05
1?
1A
0;
1G
02
1=
b10 d
b1110 `
b1110 $
b1110 .
b1110 +
b1001110 ,
#790000
b11 !
b11 /
14
18
13
15
1;
12
b11 d
b1111 `
b1111 $
b1111 .
b1111 +
b1001111 ,
#800000
0[
0V
0"
08
0@
0D
1L
b0 0
0N
b101 !
b101 /
0X
0Z
0?
0A
1K
0O
1M
0W
0\
0Y
0G
1S
0R
0^
02
0=
0I
0U
11
0c
b101 d
b0 `
b101 _
b0 $
b0 .
b101 #
b101 -
b101 *
b0 +
b1010000 ,
#810000
1@
1D
1?
1A
1>
b110 !
b110 /
04
b1 0
16
03
17
05
0;
1:
12
b110 d
b1 `
b1 $
b1 .
b1 +
b1010001 ,
#820000
0X
0[
0W
0Y
0V
0N
1L
0O
1K
0Q
1M
0J
0>
0B
14
b0 0
06
b111 !
b111 /
1@
0C
13
07
15
1?
0E
1A
1;
0:
1G
02
1=
b111 d
b10 `
b10 $
b10 .
b10 +
b1010010 ,
#830000
1X
1[
1W
1Y
1V
1N
0L
1O
0K
1Q
0M
1J
1B
0@
1C
0?
1E
0A
1>
b1000 !
b1000 /
04
b111 0
16
03
17
05
0;
1:
12
b1000 d
b11 `
b11 $
b11 .
b11 +
b1010011 ,
#840000
0D
0J
0>
0B
14
b100 0
06
0@
0C
b1001 !
b1001 /
0L
0P
13
07
15
0?
0E
0A
0K
0Q
0M
1;
0:
0G
0S
1R
02
0=
1I
b1001 d
b100 `
b100 $
b100 .
b100 +
b1010100 ,
#850000
1@
1D
1?
1A
1>
b1010 !
b1010 /
04
b101 0
16
03
17
05
0;
1:
12
b1010 d
b101 `
b101 $
b101 .
b101 +
b1010101 ,
#860000
0P
0L
0K
0M
0J
0>
0B
14
b100 0
06
b1011 !
b1011 /
1@
0C
13
07
15
1?
0E
1A
1;
0:
1G
02
1=
b1011 d
b110 `
b110 $
b110 .
b110 +
b1010110 ,
#870000
1P
1L
1K
1M
1J
1B
0@
1C
0?
1E
0A
1>
b1100 !
b1100 /
04
b111 0
16
03
17
05
0;
1:
12
b1100 d
b111 `
b111 $
b111 .
b111 +
b1010111 ,
#880000
0D
0J
0>
0B
0V
0"
14
06
0@
0C
1L
b0 0
0N
0P
b1101 !
b1101 /
1X
0Z
13
07
15
0?
0E
0A
1K
0Q
0O
1M
1W
0\
1Y
1;
0:
0G
1S
0R
1^
02
0=
0I
1U
b1101 d
b1000 `
b1000 $
b1000 .
b1000 +
b1011000 ,
#890000
1@
1D
1?
1A
1>
b1110 !
b1110 /
04
b1 0
16
03
17
05
0;
1:
12
b1110 d
b1001 `
b1001 $
b1001 .
b1001 +
b1011001 ,
#900000
0"
1X
0Z
1W
0\
1Y
0V
0N
1L
0O
1K
0Q
1M
0J
0>
0B
14
b0 0
06
b1111 !
b1111 /
1@
0C
13
07
15
1?
0E
1A
1;
0:
1G
02
1=
b1111 d
b1010 `
b1010 $
b1010 .
b1010 +
b1011010 ,
#910000
1"
0X
1Z
0W
1\
0Y
1V
1N
0L
1O
0K
1Q
0M
1J
1B
0@
1C
0?
1E
0A
1>
b0 !
b0 /
04
b111 0
16
03
17
05
0;
1:
12
1c
b0 d
b1011 `
b1011 $
b1011 .
b1011 +
b1011011 ,
#920000
0D
0J
0>
0B
14
b100 0
06
0@
0C
b1 !
b1 /
0L
0P
13
07
15
0?
0E
0A
0K
0Q
0M
1;
0:
0G
0S
1R
02
0=
1I
b1 d
b1100 `
b1100 $
b1100 .
b1100 +
b1011100 ,
#930000
1@
1D
1?
1A
1>
b10 !
b10 /
04
b101 0
16
03
17
05
0;
1:
12
b10 d
b1101 `
b1101 $
b1101 .
b1101 +
b1011101 ,
#940000
0P
0L
0K
0M
0J
0>
0B
14
b100 0
06
b11 !
b11 /
1@
0C
13
07
15
1?
0E
1A
1;
0:
1G
02
1=
b11 d
b1110 `
b1110 $
b1110 .
b1110 +
b1011110 ,
#950000
1P
1L
1K
1M
1J
1B
0@
1C
0?
1E
0A
1>
b100 !
b100 /
04
b111 0
16
03
17
05
0;
1:
12
b100 d
b1111 `
b1111 $
b1111 .
b1111 +
b1011111 ,
