adders/full_subtractor_bh.v
module full_subtractor_bh(
    input a,
    input b,
    input c,
    output reg difference,
    output reg borrow
);

always @(*) begin
difference = a ^ b ^ c;
borrow = (~a & b) | (b & c) | (~a & c);
end

endmodule

adders/full_subtractor_df.v
module full_subtractor_df (
    input a,
    input b,
    input c,
    output difference,
    output borrow
);
assign difference = a ^ b ^ c;
assign borrow = (~a & b) | (b & c) | (~a & c);
endmodule

gates/or_gate_st.v
module or_gate_st(
    input a,
    input b,
    output y
);

or(y,a,b);

endmodule

gates/and_gate_st.v
module and_gate_st(
    input a,
    input b,
    output y
);

and(y,a,b);

endmodule

gates/not_gate_st.v
module not_gate_st(
    input a,
    output y
);

not(y,a);

endmodule

gates/xor_gate_st.v
module xor_gate_st(
    input a,
    input b,
    output y
);

xor(y,a,b);

endmodule

adders/half_subtractor_st.v
`include "not_gate_st.v"
`include "xor_gate_st.v"
`include "and_gate_st.v"
module half_subtractor_st (
    input a,
    input b,
    output difference,
    output borrow
);


xor_gate_st x1(a,b,difference);
not_gate_st n1(a,x);
and_gate_st a1(x,b,borrow);

    
endmodule

adders/full_subtractor_st.v
`include "half_subtractor_st.v"
`include "or_gate_st.v"
module full_subtractor_st (
    input a,
    input b,
    input c,
    output difference,
    output borrow
);
    half_subtractor_st s1(a,b,x,y);
    half_subtractor_st s2(x,c,difference,z);
    or_gate_st o1(y,z,borrow);
    

endmodule

adders/full_subtractor_tb.v
`include "full_subtractor_st.v"
`include "full_subtractor_df.v"
`include "full_subtractor_bh.v"
module full_subtractor_tb();

reg a,b,c;
wire difference, borrow;

initial begin
    $dumpfile("subtractor.vcd");
    $dumpvars(0, full_subtractor_tb);

    $display("time\t a b c dif bor");
    $monitor("%g\t %b %b %b  %b   %b  ",
        $time, a, b, c,  difference,borrow);
    
    a = 0; b = 0; c = 0;
    #5 a = 0; b = 0; c = 1;
    #5 a = 0; b = 1; c = 0;
    #5 a = 0; b = 1; c = 1;
    #5 a = 1; b = 0; c = 0;
    #5 a = 1; b = 0; c = 1;
    #5 a = 1; b = 1; c = 0;
    #5 a = 1; b = 1; c = 1;
    #5 $finish;
end

full_subtractor_st s1(a,b,c,difference,borrow);
// full_subtractor_df s2(a,b,c,difference,borrow);
// full_subtractor_bh s3(a,b,c,difference,borrow);



endmodule

adders/subtractor.vcd
$date
	Wed Sep 11 17:01:49 2024
$end
$version
	Icarus Verilog
$end
$timescale
	1s
$end
$scope module full_subtractor_tb $end
$var wire 1 ! difference $end
$var wire 1 " borrow $end
$var reg 1 # a $end
$var reg 1 $ b $end
$var reg 1 % c $end
$scope module s1 $end
$var wire 1 # a $end
$var wire 1 $ b $end
$var wire 1 % c $end
$var wire 1 & z $end
$var wire 1 ' y $end
$var wire 1 ( x $end
$var wire 1 ! difference $end
$var wire 1 " borrow $end
$scope module o1 $end
$var wire 1 " y $end
$var wire 1 & b $end
$var wire 1 ' a $end
$upscope $end
$scope module s1 $end
$var wire 1 # a $end
$var wire 1 $ b $end
$var wire 1 ) x $end
$var wire 1 ( difference $end
$var wire 1 ' borrow $end
$scope module a1 $end
$var wire 1 $ b $end
$var wire 1 ' y $end
$var wire 1 ) a $end
$upscope $end
$scope module n1 $end
$var wire 1 # a $end
$var wire 1 ) y $end
$upscope $end
$scope module x1 $end
$var wire 1 # a $end
$var wire 1 $ b $end
$var wire 1 ( y $end
$upscope $end
$upscope $end
$scope module s2 $end
$var wire 1 ( a $end
$var wire 1 % b $end
$var wire 1 * x $end
$var wire 1 ! difference $end
$var wire 1 & borrow $end
$scope module a1 $end
$var wire 1 % b $end
$var wire 1 & y $end
$var wire 1 * a $end
$upscope $end
$scope module n1 $end
$var wire 1 ( a $end
$var wire 1 * y $end
$upscope $end
$scope module x1 $end
$var wire 1 ( a $end
$var wire 1 % b $end
$var wire 1 ! y $end
$upscope $end
$upscope $end
$upscope $end
$upscope $end
$enddefinitions $end
$comment Show the parameter values. $end
$dumpall
$end
#0
$dumpvars
1*
1)
0(
0'
0&
0%
0$
0#
0"
0!
$end
#5
1"
1&
1!
1%
#10
0*
0&
1'
1(
0%
1$
#15
0!
1%
#20
0"
1!
0'
0)
0%
0$
1#
#25
0!
1%
#30
1*
0(
0%
1$
#35
1"
1&
1!
1%
