decoders/decoder_3_to_8_st.v
`include "gates.v"
module decoder_3_to_8_st(
    input [2:0] a,
    input e,
    output [7:0] y
);

wire na0, na1, na2, ne;

not_gate_df n1(.y(na0), .a(a[0]));
not_gate_df n2(.y(na1), .a(a[1]));
not_gate_df n3(.y(na2), .a(a[2]));

three_bit_and_gate_df a1 (.y(y[0]),.a0(na0), .a1(na1), .a2(na2), .e(e));
three_bit_and_gate_df a2 (.y(y[1]),.a0(a[0]), .a1(na1), .a2(na2), .e(e));
three_bit_and_gate_df a3 (.y(y[2]),.a0(na0), .a1(a[1]), .a2(na2), .e(e));
three_bit_and_gate_df a4 (.y(y[3]),.a0(a[0]), .a1(a[1]), .a2(na2), .e(e));
three_bit_and_gate_df a5 (.y(y[4]),.a0(na0), .a1(na1), .a2(a[2]), .e(e));
three_bit_and_gate_df a6 (.y(y[5]),.a0(a[0]), .a1(na1), .a2(a[2]), .e(e));
three_bit_and_gate_df a7 (.y(y[6]),.a0(na0), .a1(a[1]), .a2(a[2]), .e(e));
three_bit_and_gate_df a8 (.y(y[7]),.a0(a[0]), .a1(a[1]), .a2(a[2]), .e(e));


endmodule

decoders/decoder_3_to_8_df.v
module decoder_3_to_8_df(
    input [2:0] a,
    input e,
    output[7:0] y
);

assign y = (e) ? (1 << a) : 8'b00000000;

endmodule

decoders/decoder_3_to_8_bh.v
module decoder_3_to_8_bh(
    input [2:0] a,
    input e,
    output reg [7:0] y
);

always @(*) begin
     y = (e) ? (1 << a) : 8'b00000000;

end

endmodule

decoders/decoder_3_to_8_tb.v
`include "decoder_3_to_8_df.v"
`include "decoder_3_to_8_st.v"
`include "decoder_3_to_8_bh.v"
module decoder_3_to_8_tb();

reg [2:0] a;
reg e;
wire [7:0] y;


// decoder_3_to_8_df d1 (
//     .a(a),
//     .e(e),
//     .y(y)
// );

// decoder_3_to_8_st d2 (
//     .a(a),
//     .e(e),
//     .y(y)
// );

decoder_3_to_8_bh d3 (
    .a(a),
    .e(e),
    .y(y)
);

initial begin
    $dumpfile("decoder38.vcd");
    $dumpvars(0, decoder_3_to_8_tb);

    $display("time\t e a     y ");
    $monitor("%g\t %b %b   %b",$time, e,a,y);

    e = 0;
    #10 e = 1; a = 3'b000;
    #10 a = 3'b001;
    #10 a = 3'b010;
    #10 a = 3'b011;
    #10 a = 3'b100; 
    #10 a = 3'b101; 
    #10 a = 3'b110; 
    #10 a = 3'b111; 
    end

endmodule

decoders/decoder38.vcd
$date
	Wed Oct  2 22:20:03 2024
$end
$version
	Icarus Verilog
$end
$timescale
	1s
$end
$scope module decoder_3_to_8_tb $end
$var wire 8 ! y [7:0] $end
$var reg 3 " a [2:0] $end
$var reg 1 # e $end
$scope module d3 $end
$var wire 3 $ a [2:0] $end
$var wire 1 # e $end
$var reg 8 % y [7:0] $end
$upscope $end
$upscope $end
$enddefinitions $end
$comment Show the parameter values. $end
$dumpall
$end
#0
$dumpvars
b0 %
bx $
0#
bx "
b0 !
$end
#10
b1 !
b1 %
b0 "
b0 $
1#
#20
b10 !
b10 %
b1 "
b1 $
#30
b100 !
b100 %
b10 "
b10 $
#40
b1000 !
b1000 %
b11 "
b11 $
#50
b10000 !
b10000 %
b100 "
b100 $
#60
b100000 !
b100000 %
b101 "
b101 $
#70
b1000000 !
b1000000 %
b110 "
b110 $
#80
b10000000 !
b10000000 %
b111 "
b111 $
